forcefield_step/__init__.py
forcefield_step/_version.py
forcefield_step/forcefield.py
forcefield_step/forcefield_parameters.py
forcefield_step/forcefield_step.py
forcefield_step/ligpargen.py
forcefield_step/tk_forcefield.py
forcefield_step/data/dreiding.frc
forcefield_step/data/lithium_battery.frc
forcefield_step/data/nacl_water.frc
forcefield_step/data/oplsaa.frc
forcefield_step/data/pcff2018.frc
forcefield_step/data/reaxff/CHLiOFSi_Yun_2017.frc
forcefield_step/data/reaxff/CHNOFSClNiPt_FC_2013.frc
forcefield_step/data/reaxff/CHNO_HNS_2014.frc
forcefield_step/data/reaxff/CHNO_RDX_2003.frc
forcefield_step/data/reaxff/CHOFe_FeOH_2010.frc
forcefield_step/data/reaxff/CHOV_VOH_2008.frc
forcefield_step/data/reaxff/CHO_cho_2008.frc
forcefield_step/data/reaxff/CH_2018.frc
forcefield_step/data/reaxff/CLiSi_Guifo_2023.frc
forcefield_step/data/reaxff/HBNO_AB_2010.frc
forcefield_step/data/reaxff/HOAu_AuO_2010.frc
forcefield_step/data/reaxff/HOZn_ZNOH_2010.frc
forcefield_step-2025.7.22.dist-info/licenses/AUTHORS.rst
forcefield_step-2025.7.22.dist-info/licenses/LICENSE
forcefield_step-2025.7.22.dist-info/METADATA
forcefield_step-2025.7.22.dist-info/WHEEL
forcefield_step-2025.7.22.dist-info/entry_points.txt
forcefield_step-2025.7.22.dist-info/top_level.txt
forcefield_step-2025.7.22.dist-info/RECORD
