Metadata-Version: 2.4
Name: forcefield_step
Version: 2025.7.22
Summary: A SEAMM plug-in for setting up a forcefield or EAM potentials for subsequent simulations.
Home-page: https://github.com/molssi-seam/forcefield_step
Author: Paul Saxe
Author-email: psaxe@molssi.org
License: BSD-3-Clause
Keywords: SEAMM,plug-in,flowchart,forcefield,EAM,OpenKIM
Platform: Linux
Platform: Mac OS-X
Platform: Unix
Platform: Windows
Classifier: Development Status :: 5 - Production/Stable
Classifier: Intended Audience :: Science/Research
Classifier: License :: OSI Approved :: BSD License
Classifier: Natural Language :: English
Classifier: Programming Language :: Python :: 3 :: Only
Classifier: Programming Language :: Python :: 3.8
Classifier: Programming Language :: Python :: 3.9
License-File: LICENSE
License-File: AUTHORS.rst
Requires-Dist: kim-query
Requires-Dist: pyperclip
Requires-Dist: rdkit
Requires-Dist: read-structure-step
Requires-Dist: seamm
Requires-Dist: seamm-ff-util
Requires-Dist: tabulate
Dynamic: author
Dynamic: author-email
Dynamic: classifier
Dynamic: description
Dynamic: description-content-type
Dynamic: home-page
Dynamic: keywords
Dynamic: license
Dynamic: license-file
Dynamic: platform
Dynamic: requires-dist
Dynamic: summary
